{
  "resources": [
    {
      "path": "data.csv",
      "name": "data",
      "profile": "tabular-data-resource",
      "scheme": "file",
      "format": "csv",
      "hashing": "md5",
      "encoding": "cp1252",
      "schema": {
        "fields": [
          {
            "name": "Year",
            "type": "integer"
          },
          {
            "name": "Ec_activ",
            "type": "string",
            "constraints": {
              "enum": [
                "11_agricul",
                "2_indus",
                "7_constr",
                "14_motor_veh",
                "group_label_269",
                "16_cater",
                "17_telecom",
                "18_insurance",
                "19_estate",
                "20_scientific",
                "21_support",
                "23_educ",
                "group_label_271",
                "25_arts",
                "26_other_serv",
                ""
              ]
            }
          },
          {
            "name": "Value",
            "type": "number"
          }
        ]
      }
    }
  ],
  "profile": "data-package",
  "name": "8-4-1",
  "title": "global_indicators.8-4-1-title"
}