{
  "resources": [
    {
      "path": "data.csv",
      "name": "data",
      "profile": "tabular-data-resource",
      "scheme": "file",
      "format": "csv",
      "hashing": "md5",
      "encoding": "cp1252",
      "schema": {
        "fields": [
          {
            "name": "Year",
            "type": "integer",
            "title": "Year"
          },
          {
            "name": "Region",
            "type": "string",
            "constraints": {
              "enum": [
                "Ukraine",
                "city Sevastopol",
                "Autonomous Republic of Crimea",
                "Vinnytsya",
                "Volyn",
                "Dnipropetrovsk",
                "Donetsk",
                "Zhytomyr",
                "Zakarpattya",
                "Zaporizhzhya",
                "Ivano-Frankivsk",
                "Kyiv",
                "Kirovohrad",
                "Luhansk",
                "Lviv",
                "Mykolayiv",
                "Odesa",
                "Poltava",
                "Rivne",
                "Sumy",
                "Ternopil",
                "Kharkiv",
                "Kherson",
                "Khmelnytskiy",
                "Cherkasy",
                "Chernivtsi",
                "Chernihiv",
                "the city of Kyiv",
                ""
              ]
            },
            "title": "Region"
          },
          {
            "name": "Sex",
            "type": "string",
            "constraints": {
              "enum": [
                "women",
                "men",
                ""
              ]
            },
            "title": "Sex"
          },
          {
            "name": "Age",
            "type": "string",
            "constraints": {
              "enum": [
                "31.2",
                "30.4",
                "24.7",
                "29.6",
                "45.8",
                "70.2",
                "158.2",
                "416.2",
                "577.7",
                "1397.0",
                ""
              ]
            },
            "title": "Age"
          },
          {
            "name": "Value",
            "type": "number",
            "title": "Value"
          }
        ]
      }
    }
  ],
  "profile": "data-package",
  "name": "10-1-2",
  "title": "Ratio of the average monthly wage (income) of the 10th and 1st decile groups of employees (decile coefficient), times"
}