{"data":{"Year":[2015,2016,2017,2018,2019,2020,2021,2022,2023,2023,2024,2024,2024,2024,2024,2024,2024,2024,2024,2024],"By river basins":[null,null,null,null,null,null,null,null,null,null,null,"azov_river_basin_area","black_sea_river_basin_area","crimea_river_basin_area","danube_river_basin_area","dniester_river_basin_area","dnipro_river_basin_area","don_river_basin_area","southern_bug_river_basin_area","vistula_river_basin_area"],"Value":[null,null,null,null,null,null,null,null,null,null,9.0,1.0,1.0,1.0,1.0,1.0,1.0,1.0,1.0,1.0]},"edges":[]}