{
  "resources": [
    {
      "path": "data.csv",
      "name": "data",
      "profile": "tabular-data-resource",
      "scheme": "file",
      "format": "csv",
      "hashing": "md5",
      "encoding": "utf-8",
      "schema": {
        "fields": [
          {
            "name": "Year",
            "type": "integer",
            "title": "Рік"
          },
          {
            "name": "Group",
            "type": "string",
            "constraints": {
              "enum": [
                "з них внутрішньо переміщені особи",
                ""
              ]
            },
            "title": "Група"
          },
          {
            "name": "Type of residence",
            "type": "string",
            "constraints": {
              "enum": [
                "міська",
                "сільська",
                ""
              ]
            },
            "title": "Місцевість проживання"
          },
          {
            "name": "Age",
            "type": "number",
            "constraints": {
              "enum": [
                ""
              ]
            },
            "title": "Вік"
          },
          {
            "name": "Sex",
            "type": "string",
            "constraints": {
              "enum": [
                "жінки",
                "чоловіки",
                ""
              ]
            },
            "title": "Стать"
          },
          {
            "name": "By age of the housing provided to the participants",
            "type": "number",
            "constraints": {
              "enum": [
                ""
              ]
            },
            "title": "за віком житла, яким забезпечено учасників"
          },
          {
            "name": "Value",
            "type": "number",
            "title": "Value"
          }
        ]
      }
    }
  ],
  "profile": "data-package",
  "name": "11-1-1",
  "title": "Частка сімей/громадян (сумарно усі члени сім’ї), які скористалися житловими програмами, у загальній кількості сімей/громадян, які потребують житла, відсотків"
}